autodistill_yolov5/__init__.py
autodistill_yolov5/yolov5_model.py
src/__init__.py
src/hello.py
autodistill_yolov5-0.1.2.dist-info/LICENSE
autodistill_yolov5-0.1.2.dist-info/METADATA
autodistill_yolov5-0.1.2.dist-info/WHEEL
autodistill_yolov5-0.1.2.dist-info/top_level.txt
autodistill_yolov5-0.1.2.dist-info/RECORD
