Metadata-Version: 2.1
Name: autodistill-yolov5
Version: 0.1.2
Summary: YOLOv5 module for use with Autodistill
Home-page: https://github.com/autodistill/autodistill-yolov5
Author: Roboflow
Author-email: support@roboflow.com
Classifier: Programming Language :: Python :: 3
Classifier: License :: OSI Approved :: GNU Affero General Public License v3 or later (AGPLv3+)
Classifier: Operating System :: OS Independent
Requires-Python: >=3.7
License-File: LICENSE
Requires-Dist: yolov5
Requires-Dist: autodistill
Requires-Dist: supervision (==0.9.0)
Requires-Dist: torch
Provides-Extra: dev
Requires-Dist: flake8 ; extra == 'dev'
Requires-Dist: black (==22.3.0) ; extra == 'dev'
Requires-Dist: isort ; extra == 'dev'
Requires-Dist: twine ; extra == 'dev'
Requires-Dist: pytest ; extra == 'dev'
Requires-Dist: wheel ; extra == 'dev'
